xiaochuanhttpsproxy/__init__.py
xiaochuanhttpsproxy/api.py
xiaochuanhttpsproxy/enter.py
xiaochuanhttpsproxy/filter.py
xiaochuanhttpsproxy/getip.py
xiaochuanhttpsproxy/start.py
xiaochuanhttpsproxy-0.0.2.dist-info/LICENSE
xiaochuanhttpsproxy-0.0.2.dist-info/METADATA
xiaochuanhttpsproxy-0.0.2.dist-info/WHEEL
xiaochuanhttpsproxy-0.0.2.dist-info/top_level.txt
xiaochuanhttpsproxy-0.0.2.dist-info/RECORD
