Metadata-Version: 2.1
Name: xiaochuanhttpsproxy
Version: 0.0.2
Summary: https proxy api
Home-page: https://github.com/2239559319/xiaochuanhttpsproxy
Author: 小川
Author-email: w2239559319@outlook.com
License: UNKNOWN
Platform: UNKNOWN
Classifier: Programming Language :: Python :: 3
Classifier: License :: OSI Approved :: Apache Software License
Classifier: Operating System :: OS Independent
